commit_companion/__init__.py
commit_companion/ai_utils.py
commit_companion/cli.py
commit_companion/git_utils.py
commit_companion/main.py
commit_companion/utils.py
commit_companion-0.1.2.dist-info/entry_points.txt
commit_companion-0.1.2.dist-info/licenses/LICENSE
commit_companion-0.1.2.dist-info/WHEEL
commit_companion-0.1.2.dist-info/METADATA
commit_companion-0.1.2.dist-info/RECORD
