Metadata-Version: 2.4
Name: commit-companion
Version: 0.1.2
Summary: Smarter Git commit messages using GPT.
Keywords: git,cli,openai,commit,automation
Author-email: Zack Nelson <zacknelson15@gmail.com>
Requires-Python: >=3.8
License-Expression: MIT
Classifier: Programming Language :: Python :: 3
Classifier: Programming Language :: Python :: 3.8
Classifier: Programming Language :: Python :: 3.9
Classifier: Programming Language :: Python :: 3.10
Classifier: Programming Language :: Python :: 3.11
Classifier: Operating System :: OS Independent
License-File: LICENSE
Project-URL: Home, https://github.com/nelson-zack/commit-companion
